colrev_asreview/.colrev_endpoints.json
colrev_asreview/__init__.py
colrev_asreview/colrev_asreview.py
colrev_asreview-0.1.0.dist-info/METADATA
colrev_asreview-0.1.0.dist-info/WHEEL
colrev_asreview-0.1.0.dist-info/RECORD
