Metadata-Version: 2.1
Name: colrev-asreview
Version: 0.1.0
Summary: 
Author: Gerit Wagner
Author-email: gerit.wagner@hec.ca
Requires-Python: >=3.8,<4
Classifier: Programming Language :: Python :: 3
Classifier: Programming Language :: Python :: 3.8
Classifier: Programming Language :: Python :: 3.9
Classifier: Programming Language :: Python :: 3.10
Classifier: Programming Language :: Python :: 3.11
Requires-Dist: asreview (>=1.2,<2.0)
Requires-Dist: colrev (>=0.9.0)
Requires-Dist: dataclasses-jsonschema (>=2.16.0,<3.0.0)
